dora_phi4/__init__.py
dora_phi4/__main__.py
dora_phi4/main.py
dora_phi4-0.3.13.dist-info/METADATA
dora_phi4-0.3.13.dist-info/WHEEL
dora_phi4-0.3.13.dist-info/entry_points.txt
dora_phi4-0.3.13.dist-info/top_level.txt
dora_phi4-0.3.13.dist-info/RECORD
