Metadata-Version: 2.4
Name: dora-phi4
Version: 0.3.13
Summary: DORA node for Phi-4 multimodal model
Author-email: Somay <ssomay2002@gmail.com>
License: MIT
Requires-Python: >=3.10
Requires-Dist: dora-rs>=0.3.9
Requires-Dist: torch==2.6.0
Requires-Dist: torchvision==0.21.0
Requires-Dist: transformers==4.48.2
Requires-Dist: accelerate==1.3.0
Requires-Dist: soundfile==0.13.1
Requires-Dist: pillow==11.1.0
Requires-Dist: scipy==1.15.2
Requires-Dist: backoff==2.2.1
Requires-Dist: peft==0.13.2
Requires-Dist: opencv-python
Requires-Dist: requests
